ga/__init__.py
ga/codec.py
ga/exception.py
ga/ga.py
ga/genotype.py
ga/individual.py
ga/phenotype.py
ga/population.py
ga/selector.py
ga/lib/__init__.py
ga/lib/iterable.py
ga/plugins/__init__.py
ga/plugins/plugin_type.py
ga/plugins/plugins.py
ga_cm/__init__.py
ga_cm/cm_plugin.py
ga_codec/__init__.py
ga_codec/codec_plugin.py
ga_generate/__init__.py
ga_generate/generate_plugin.py
ga_iter/__init__.py
ga_iter/stop_iter_plugin.py
ga_selector/__init__.py
ga_selector/selector.py
GA_Common-0.1.dist-info/LICENSE
GA_Common-0.1.dist-info/METADATA
GA_Common-0.1.dist-info/WHEEL
GA_Common-0.1.dist-info/top_level.txt
GA_Common-0.1.dist-info/RECORD
