Metadata-Version: 2.1
Name: GA-Common
Version: 0.1
Summary: Easy Use GA
Home-page: https://github.com/lipopo/ga
Author: lipo
Author-email: lipo8081@gmail.com
License: UNKNOWN
Platform: UNKNOWN
Classifier: Programming Language :: Python :: 3
Classifier: License :: OSI Approved :: MIT License
Classifier: Operating System :: OS Independent
Requires-Python: >3.0
